mcp_web_fetch/__init__.py
mcp_web_fetch/fetch.py
mcp_web_fetch-0.3.0.dist-info/METADATA
mcp_web_fetch-0.3.0.dist-info/WHEEL
mcp_web_fetch-0.3.0.dist-info/entry_points.txt
mcp_web_fetch-0.3.0.dist-info/RECORD
