Metadata-Version: 2.4
Name: mcp-web-fetch
Version: 0.3.0
Summary: Fetch data from ANY website
Requires-Python: <3.13,>=3.12
Requires-Dist: httpx>=0.28.1
Requires-Dist: mcp[cli]>=1.9.0
Requires-Dist: pydantic>=2.10
Requires-Dist: requests>=2.32.2
